.gitignore
MANIFEST.in
README.md
make.sh
pyproject.toml
requirements.txt
setup.cfg
setup.py
tomake.txt
docs/.buildinfo
docs/.nojekyll
docs/Makefile
docs/apiref.html
docs/genindex.html
docs/index.html
docs/installation.html
docs/make.bat
docs/objects.inv
docs/py-modindex.html
docs/search.html
docs/searchindex.js
docs/tomake.txt
docs/usage.html
docs/usage.ipynb
docs/_images/usage_30_0.png
docs/_images/usage_34_0.png
docs/_images/usage_35_0.png
docs/_images/usage_36_0.png
docs/_images/usage_37_0.png
docs/_images/usage_39_0.png
docs/_images/usage_40_0.png
docs/_images/usage_41_0.png
docs/_images/usage_44_0.png
docs/_images/usage_45_0.png
docs/_images/usage_46_0.png
docs/_images/usage_51_0.png
docs/_images/usage_52_0.png
docs/_images/usage_53_0.png
docs/_images/usage_7_0.png
docs/_modules/index.html
docs/_modules/pyblip/blip.html
docs/_modules/pyblip/changepoint.html
docs/_modules/pyblip/create_groups.html
docs/_modules/pyblip/create_groups_cts.html
docs/_modules/pyblip/ecc.html
docs/_modules/pyblip/weight_fns.html
docs/_modules/pyblip/linear/linear.html
docs/_modules/pyblip/nprior/nprior.html
docs/_modules/pyblip/probit/probit.html
docs/_sources/apiref.rst.txt
docs/_sources/index.rst.txt
docs/_sources/installation.rst.txt
docs/_sources/usage.ipynb.txt
docs/_static/alabaster.css
docs/_static/basic.css
docs/_static/custom.css
docs/_static/doctools.js
docs/_static/documentation_options.js
docs/_static/file.png
docs/_static/graphviz.css
docs/_static/jquery-3.5.1.js
docs/_static/jquery.js
docs/_static/language_data.js
docs/_static/minus.png
docs/_static/plus.png
docs/_static/pygments.css
docs/_static/searchtools.js
docs/_static/underscore-1.13.1.js
docs/_static/underscore-1.3.1.js
docs/_static/underscore.js
docs/_static/css/badge_only.css
docs/_static/css/theme.css
docs/_static/css/fonts/Roboto-Slab-Bold.woff
docs/_static/css/fonts/Roboto-Slab-Bold.woff2
docs/_static/css/fonts/Roboto-Slab-Regular.woff
docs/_static/css/fonts/Roboto-Slab-Regular.woff2
pyblip.egg-info/PKG-INFO
pyblip.egg-info/SOURCES.txt
pyblip.egg-info/dependency_links.txt
pyblip.egg-info/requires.txt
pyblip.egg-info/top_level.txt
