Metadata-Version: 2.1
Name: pyblip
Version: 0.4.2
Summary: Bayesian Linear Programming (BLiP) in Python
Home-page: https://github.com/amspector100/pyblip
Author: Asher Spector
Author-email: amspector100@gmail.com
Classifier: Programming Language :: Python :: 3
Classifier: License :: OSI Approved :: MIT License
Classifier: Operating System :: OS Independent
Requires-Python: >=3.6
